{
  "groups": [
    {
      "name": "security",
      "type": "com.oauth.jwt.ds.config.SecurityProperties",
      "sourceType": "com.oauth.jwt.ds.config.SecurityProperties"
    },
    {
      "name": "security.jwt",
      "type": "com.oauth.jwt.ds.config.SecurityProperties$JwtProperties",
      "sourceType": "com.oauth.jwt.ds.config.SecurityProperties",
      "sourceMethod": "public com.oauth.jwt.ds.config.SecurityProperties.JwtProperties getJwt() "
    }
  ],
  "properties": [
    {
      "name": "security.jwt.public-key",
      "type": "org.springframework.core.io.Resource",
      "sourceType": "com.oauth.jwt.ds.config.SecurityProperties$JwtProperties"
    }
  ],
  "hints": []
}